<?xml version="1.0" encoding="GBK" standalone="yes" ?>

<metalib tagsetversion="1" name="genius_rectify" version="10" >
	<macro name="GENIUS_RECTIFY_LEN"      value="64" />

	<struct name="genius_rectify_conf" version ="10" >
		<entry name="OldBinName" type="string" size="GENIUS_RECTIFY_LEN" defaultvalue="./GeniusCareerDef_old.bin"  />
		<entry name="NewBinName" type="string" size="GENIUS_RECTIFY_LEN" defaultvalue="./GeniusCareerDef.bin"  />
		<entry name="MetaFile" type="string" size="128" defaultvalue="./role_db_meta.tdr"  desc="role_db_meta.tdr" />
		<entry name="DBName" 	 type="string" size="GENIUS_RECTIFY_LEN" desc="源角色数据库信息"/>
		<entry name="DBConnect"  type="string" size="GENIUS_RECTIFY_LEN"   />
		<entry name="DBUser"     type="string" size="GENIUS_RECTIFY_LEN"   />
		<entry name="DBPasswd"   type="string" size="GENIUS_RECTIFY_LEN"  />
	</struct>
</metalib>